setup.cfg
setup.py
pyf/__init__.py
pyf.egg-info/PKG-INFO
pyf.egg-info/SOURCES.txt
pyf.egg-info/dependency_links.txt
pyf.egg-info/entry_points.txt
pyf.egg-info/namespace_packages.txt
pyf.egg-info/not-zip-safe
pyf.egg-info/requires.txt
pyf.egg-info/top_level.txt