Metadata-Version: 1.0
Name: pyf
Version: 1.3
Summary: Pyf is a dataflow library
Home-page: http://pyfproject.org
Author: Jonathan Schemoul, Florent Aide, Jerome Collette
Author-email: jonathan.schemoul@gmail.com, florent.aide@gmail.com, collette.jerome@gmail.com
License: MIT
Platform: UNKNOWN
Classifier: Topic :: Software Development :: Libraries :: Python Modules
Classifier: Development Status :: 4 - Beta
